pyfidelius/__init__.py
pyfidelius/cryptography/__init__.py
pyfidelius/cryptography/cryptography.py
pyfidelius/fidelius-cli-1.2.0/bin/fidelius-cli
pyfidelius/fidelius-cli-1.2.0/bin/fidelius-cli.bat
pyfidelius/fidelius-cli-1.2.0/lib/bcprov-jdk18on-1.71.jar
pyfidelius/fidelius-cli-1.2.0/lib/fidelius-cli-1.2.0.jar
pyfidelius/fidelius-cli-1.2.0/lib/gson-2.9.0.jar
pyfidelius/requirement_check/__init__.py
pyfidelius/requirement_check/requirement_check.py
pyfidelius-0.0.4.dist-info/LICENSE
pyfidelius-0.0.4.dist-info/METADATA
pyfidelius-0.0.4.dist-info/WHEEL
pyfidelius-0.0.4.dist-info/top_level.txt
pyfidelius-0.0.4.dist-info/RECORD
