Metadata-Version: 2.1
Name: pyfidelius
Version: 0.0.4
Summary: Python SDK for Fidelius CLI, a tool designed for ECDH cryptography.
Home-page: https://github.com/nikhil25803/pyfidelius
Author: Nikhil Raj
Author-email: nikhil25803@gmail.com
Classifier: Programming Language :: Python :: 3
Classifier: License :: OSI Approved :: MIT License
Classifier: Operating System :: OS Independent
Requires-Python: >=3.9
License-File: LICENSE
Requires-Dist: rich
Provides-Extra: testing
Requires-Dist: pytest >=8.2.1 ; extra == 'testing'
Requires-Dist: flake8 >=3.9 ; extra == 'testing'
